{"success":true,"message":"Energy gift initiated. Proceed to payment.","requestId":"69821fffeac6dbf6206ccc53","sellerId":"p2p.terrarexenergy.com","gifterId":"did:rcw:consumption-153290082-1769510072989","transactionId":"44f0ef6a-8a88-4134-bbc7-6c542c3167a8","orderId":"order-44f0ef6a-8a88-4134-bbc7-6c542c3167a8","status":"INITIATED","amount":0.5,"paymentDetails":{"@context":"https://raw.githubusercontent.com/beckn/protocol-specifications-new/refs/heads/main/schema/core/v2/context.jsonld","@type":"beckn:Payment","beckn:id":"payment-44f0ef6a-8a88-4134-bbc7-6c542c3167a8","beckn:amount":{"currency":"INR","value":75.5},"beckn:beneficiary":"BPP","beckn:paymentStatus":"AUTHORIZED","beckn:paymentAttributes":{"@context":"https://raw.githubusercontent.com/beckn/protocol-specifications-new/refs/heads/main/schema/PaymentSettlement/v1/context.jsonld","@type":"PaymentSettlement","settlementAccounts":[{"beneficiaryId":"p2p.terrarexenergy.com","accountHolderName":"Terrarex Energy Trading Pvt Ltd","accountNumber":"50200087654321","ifscCode":"HDFC0001729","bankName":"HDFC Bank","vpa":"terrarex.energy@hdfcbank"}]}}}