[
  {
    "date": "2026-01-27",
    "hourly": [
      { "hour": "06:00", "excess_kwh": 0.0 },
      { "hour": "07:00", "excess_kwh": 0.0 },
      { "hour": "08:00", "excess_kwh": 5.0 },
      { "hour": "09:00", "excess_kwh": 9.64 },
      { "hour": "10:00", "excess_kwh": 15.51 },
      { "hour": "11:00", "excess_kwh": 18.39 },
      { "hour": "12:00", "excess_kwh": 20.37 },
      { "hour": "13:00", "excess_kwh": 19.57 },
      { "hour": "14:00", "excess_kwh": 18.87 },
      { "hour": "15:00", "excess_kwh": 14.41 },
      { "hour": "16:00", "excess_kwh": 5.0 },
      { "hour": "17:00", "excess_kwh": 0.0 },
      { "hour": "18:00", "excess_kwh": 0.0 },
      { "hour": "19:00", "excess_kwh": 0.0 },
      { "hour": "20:00", "excess_kwh": 0.0 },
      { "hour": "21:00", "excess_kwh": 0.0 },
      { "hour": "22:00", "excess_kwh": 0.0 },
      { "hour": "23:00", "excess_kwh": 0.0 }
    ]
  },
  {
    "date": "2026-01-28",
    "hourly": [
      { "hour": "00:00", "excess_kwh": 0.0 },
      { "hour": "01:00", "excess_kwh": 0.0 },
      { "hour": "02:00", "excess_kwh": 0.0 },
      { "hour": "03:00", "excess_kwh": 0.0 },
      { "hour": "04:00", "excess_kwh": 0.0 },
      { "hour": "05:00", "excess_kwh": 0.0 },
      { "hour": "06:00", "excess_kwh": 0.0 },
      { "hour": "07:00", "excess_kwh": 0.0 },
      { "hour": "08:00", "excess_kwh": 5.0 },
      { "hour": "09:00", "excess_kwh": 8.61 },
      { "hour": "10:00", "excess_kwh": 16.64 },
      { "hour": "11:00", "excess_kwh": 17.04 },
      { "hour": "12:00", "excess_kwh": 19.01 },
      { "hour": "13:00", "excess_kwh": 18.28 },
      { "hour": "14:00", "excess_kwh": 16.87 },
      { "hour": "15:00", "excess_kwh": 12.55 },
      { "hour": "16:00", "excess_kwh": 5.0 },
      { "hour": "17:00", "excess_kwh": 0.0 },
      { "hour": "18:00", "excess_kwh": 0.0 },
      { "hour": "19:00", "excess_kwh": 0.0 },
      { "hour": "20:00", "excess_kwh": 0.0 },
      { "hour": "21:00", "excess_kwh": 0.0 },
      { "hour": "22:00", "excess_kwh": 0.0 },
      { "hour": "23:00", "excess_kwh": 0.0 }
    ]
  },
  {
    "date": "2026-01-29",
    "hourly": [
      { "hour": "00:00", "excess_kwh": 0.0 },
      { "hour": "01:00", "excess_kwh": 0.0 },
      { "hour": "02:00", "excess_kwh": 0.0 },
      { "hour": "03:00", "excess_kwh": 0.0 },
      { "hour": "04:00", "excess_kwh": 0.0 },
      { "hour": "05:00", "excess_kwh": 0.0 },
      { "hour": "06:00", "excess_kwh": 0.0 },
      { "hour": "07:00", "excess_kwh": 0.0 },
      { "hour": "08:00", "excess_kwh": 5.0 },
      { "hour": "09:00", "excess_kwh": 6.69 },
      { "hour": "10:00", "excess_kwh": 16.07 },
      { "hour": "11:00", "excess_kwh": 17.2 },
      { "hour": "12:00", "excess_kwh": 19.07 },
      { "hour": "13:00", "excess_kwh": 18.22 },
      { "hour": "14:00", "excess_kwh": 16.61 },
      { "hour": "15:00", "excess_kwh": 11.97 },
      { "hour": "16:00", "excess_kwh": 5.0 },
      { "hour": "17:00", "excess_kwh": 0.0 },
      { "hour": "18:00", "excess_kwh": 0.0 },
      { "hour": "19:00", "excess_kwh": 0.0 },
      { "hour": "20:00", "excess_kwh": 0.0 },
      { "hour": "21:00", "excess_kwh": 0.0 },
      { "hour": "22:00", "excess_kwh": 0.0 },
      { "hour": "23:00", "excess_kwh": 0.0 }
    ]
  },
  {
    "date": "2026-01-30",
    "hourly": [
      { "hour": "00:00", "excess_kwh": 0.0 },
      { "hour": "01:00", "excess_kwh": 0.0 },
      { "hour": "02:00", "excess_kwh": 0.0 },
      { "hour": "03:00", "excess_kwh": 0.0 },
      { "hour": "04:00", "excess_kwh": 0.0 },
      { "hour": "05:00", "excess_kwh": 0.0 },
      { "hour": "06:00", "excess_kwh": 0.0 },
      { "hour": "07:00", "excess_kwh": 0.0 },
      { "hour": "08:00", "excess_kwh": 5.0 },
      { "hour": "09:00", "excess_kwh": 8.3 },
      { "hour": "10:00", "excess_kwh": 17.29 },
      { "hour": "11:00", "excess_kwh": 17.64 },
      { "hour": "12:00", "excess_kwh": 19.34 },
      { "hour": "13:00", "excess_kwh": 18.51 },
      { "hour": "14:00", "excess_kwh": 17.39 },
      { "hour": "15:00", "excess_kwh": 12.71 },
      { "hour": "16:00", "excess_kwh": 5.0 },
      { "hour": "17:00", "excess_kwh": 0.0 },
      { "hour": "18:00", "excess_kwh": 0.0 },
      { "hour": "19:00", "excess_kwh": 0.0 },
      { "hour": "20:00", "excess_kwh": 0.0 },
      { "hour": "21:00", "excess_kwh": 0.0 },
      { "hour": "22:00", "excess_kwh": 0.0 },
      { "hour": "23:00", "excess_kwh": 0.0 }
    ]
  },
  {
    "date": "2026-01-31",
    "hourly": [
      { "hour": "00:00", "excess_kwh": 0.0 },
      { "hour": "01:00", "excess_kwh": 0.0 },
      { "hour": "02:00", "excess_kwh": 0.0 },
      { "hour": "03:00", "excess_kwh": 0.0 },
      { "hour": "04:00", "excess_kwh": 0.0 },
      { "hour": "05:00", "excess_kwh": 0.0 },
      { "hour": "06:00", "excess_kwh": 0.0 },
      { "hour": "07:00", "excess_kwh": 0.0 },
      { "hour": "08:00", "excess_kwh": 5.0 },
      { "hour": "09:00", "excess_kwh": 6.19 },
      { "hour": "10:00", "excess_kwh": 16.92 },
      { "hour": "11:00", "excess_kwh": 16.45 },
      { "hour": "12:00", "excess_kwh": 18.46 },
      { "hour": "13:00", "excess_kwh": 17.92 },
      { "hour": "14:00", "excess_kwh": 8.61 },
      { "hour": "15:00", "excess_kwh": 6.73 },
      { "hour": "16:00", "excess_kwh": 5.0 },
      { "hour": "17:00", "excess_kwh": 0.0 },
      { "hour": "18:00", "excess_kwh": 0.0 },
      { "hour": "19:00", "excess_kwh": 0.0 },
      { "hour": "20:00", "excess_kwh": 0.0 },
      { "hour": "21:00", "excess_kwh": 0.0 },
      { "hour": "22:00", "excess_kwh": 0.0 },
      { "hour": "23:00", "excess_kwh": 0.0 }
    ]
  },
  {
    "date": "2026-02-01",
    "hourly": [
      { "hour": "00:00", "excess_kwh": 0.0 },
      { "hour": "01:00", "excess_kwh": 0.0 },
      { "hour": "02:00", "excess_kwh": 0.0 },
      { "hour": "03:00", "excess_kwh": 0.0 },
      { "hour": "04:00", "excess_kwh": 0.0 },
      { "hour": "05:00", "excess_kwh": 0.0 },
      { "hour": "06:00", "excess_kwh": 0.0 },
      { "hour": "07:00", "excess_kwh": 0.0 },
      { "hour": "08:00", "excess_kwh": 5.0 },
      { "hour": "09:00", "excess_kwh": 8.87 },
      { "hour": "10:00", "excess_kwh": 16.53 },
      { "hour": "11:00", "excess_kwh": 16.14 },
      { "hour": "12:00", "excess_kwh": 18.83 },
      { "hour": "13:00", "excess_kwh": 15.32 },
      { "hour": "14:00", "excess_kwh": 16.2 },
      { "hour": "15:00", "excess_kwh": 5.16 },
      { "hour": "16:00", "excess_kwh": 5.0 },
      { "hour": "17:00", "excess_kwh": 0.0 },
      { "hour": "18:00", "excess_kwh": 0.0 },
      { "hour": "19:00", "excess_kwh": 0.0 },
      { "hour": "20:00", "excess_kwh": 0.0 },
      { "hour": "21:00", "excess_kwh": 0.0 },
      { "hour": "22:00", "excess_kwh": 0.0 },
      { "hour": "23:00", "excess_kwh": 0.0 }
    ]
  },
  {
    "date": "2026-02-02",
    "hourly": [
      { "hour": "00:00", "excess_kwh": 0.0 },
      { "hour": "01:00", "excess_kwh": 0.0 },
      { "hour": "02:00", "excess_kwh": 0.0 },
      { "hour": "03:00", "excess_kwh": 0.0 },
      { "hour": "04:00", "excess_kwh": 0.0 },
      { "hour": "05:00", "excess_kwh": 0.0 },
      { "hour": "06:00", "excess_kwh": 0.0 },
      { "hour": "07:00", "excess_kwh": 0.0 },
      { "hour": "08:00", "excess_kwh": 5.0 },
      { "hour": "09:00", "excess_kwh": 9.02 },
      { "hour": "10:00", "excess_kwh": 16.36 },
      { "hour": "11:00", "excess_kwh": 16.41 },
      { "hour": "12:00", "excess_kwh": 19.26 },
      { "hour": "13:00", "excess_kwh": 11.32 },
      { "hour": "14:00", "excess_kwh": 18.03 },
      { "hour": "15:00", "excess_kwh": 13.31 },
      { "hour": "16:00", "excess_kwh": 5.0 },
      { "hour": "17:00", "excess_kwh": 0.0 },
      { "hour": "18:00", "excess_kwh": 0.0 },
      { "hour": "19:00", "excess_kwh": 0.0 },
      { "hour": "20:00", "excess_kwh": 0.0 },
      { "hour": "21:00", "excess_kwh": 0.0 },
      { "hour": "22:00", "excess_kwh": 0.0 },
      { "hour": "23:00", "excess_kwh": 0.0 }
    ]
  },
  {
    "date": "2026-02-03",
    "hourly": [
      { "hour": "00:00", "excess_kwh": 0.0 },
      { "hour": "01:00", "excess_kwh": 0.0 },
      { "hour": "02:00", "excess_kwh": 0.0 },
      { "hour": "03:00", "excess_kwh": 0.0 },
      { "hour": "04:00", "excess_kwh": 0.0 },
      { "hour": "05:00", "excess_kwh": 0.0 },
      { "hour": "06:00", "excess_kwh": 0.0 },
      { "hour": "07:00", "excess_kwh": 0.0 },
      { "hour": "08:00", "excess_kwh": 5.0 },
      { "hour": "09:00", "excess_kwh": 9.02 },
      { "hour": "10:00", "excess_kwh": 16.36 },
      { "hour": "11:00", "excess_kwh": 16.41 },
      { "hour": "12:00", "excess_kwh": 19.26 },
      { "hour": "13:00", "excess_kwh": 11.32 },
      { "hour": "14:00", "excess_kwh": 18.03 },
      { "hour": "15:00", "excess_kwh": 13.31 },
      { "hour": "16:00", "excess_kwh": 5.0 },
      { "hour": "17:00", "excess_kwh": 0.0 },
      { "hour": "18:00", "excess_kwh": 0.0 },
      { "hour": "19:00", "excess_kwh": 0.0 },
      { "hour": "20:00", "excess_kwh": 0.0 },
      { "hour": "21:00", "excess_kwh": 0.0 },
      { "hour": "22:00", "excess_kwh": 0.0 },
      { "hour": "23:00", "excess_kwh": 0.0 }
    ]
  },
  {
    "date": "2026-02-04",
    "hourly": [
      { "hour": "00:00", "excess_kwh": 0.0 },
      { "hour": "01:00", "excess_kwh": 0.0 },
      { "hour": "02:00", "excess_kwh": 0.0 },
      { "hour": "03:00", "excess_kwh": 0.0 },
      { "hour": "04:00", "excess_kwh": 0.0 },
      { "hour": "05:00", "excess_kwh": 0.0 },
      { "hour": "06:00", "excess_kwh": 0.0 },
      { "hour": "07:00", "excess_kwh": 0.0 },
      { "hour": "08:00", "excess_kwh": 5.0 },
      { "hour": "09:00", "excess_kwh": 9.02 },
      { "hour": "10:00", "excess_kwh": 16.36 },
      { "hour": "11:00", "excess_kwh": 16.41 },
      { "hour": "12:00", "excess_kwh": 19.26 },
      { "hour": "13:00", "excess_kwh": 11.32 },
      { "hour": "14:00", "excess_kwh": 18.03 },
      { "hour": "15:00", "excess_kwh": 13.31 },
      { "hour": "16:00", "excess_kwh": 5.0 },
      { "hour": "17:00", "excess_kwh": 0.0 },
      { "hour": "18:00", "excess_kwh": 0.0 },
      { "hour": "19:00", "excess_kwh": 0.0 },
      { "hour": "20:00", "excess_kwh": 0.0 },
      { "hour": "21:00", "excess_kwh": 0.0 },
      { "hour": "22:00", "excess_kwh": 0.0 },
      { "hour": "23:00", "excess_kwh": 0.0 }
    ]
  },
  {
    "date": "2026-02-05",
    "hourly": [
      { "hour": "00:00", "excess_kwh": 0.0 },
      { "hour": "01:00", "excess_kwh": 0.0 },
      { "hour": "02:00", "excess_kwh": 0.0 },
      { "hour": "03:00", "excess_kwh": 0.0 },
      { "hour": "04:00", "excess_kwh": 0.0 },
      { "hour": "05:00", "excess_kwh": 0.0 },
      { "hour": "06:00", "excess_kwh": 0.0 },
      { "hour": "07:00", "excess_kwh": 0.0 },
      { "hour": "08:00", "excess_kwh": 5.0 },
      { "hour": "09:00", "excess_kwh": 9.02 },
      { "hour": "10:00", "excess_kwh": 16.36 },
      { "hour": "11:00", "excess_kwh": 16.41 },
      { "hour": "12:00", "excess_kwh": 19.26 },
      { "hour": "13:00", "excess_kwh": 11.32 },
      { "hour": "14:00", "excess_kwh": 18.03 },
      { "hour": "15:00", "excess_kwh": 13.31 },
      { "hour": "16:00", "excess_kwh": 5.0 },
      { "hour": "17:00", "excess_kwh": 0.0 },
      { "hour": "18:00", "excess_kwh": 0.0 },
      { "hour": "19:00", "excess_kwh": 0.0 },
      { "hour": "20:00", "excess_kwh": 0.0 },
      { "hour": "21:00", "excess_kwh": 0.0 },
      { "hour": "22:00", "excess_kwh": 0.0 },
      { "hour": "23:00", "excess_kwh": 0.0 }
    ]
  },
  {
    "date": "2026-02-06",
    "hourly": [
      { "hour": "00:00", "excess_kwh": 0.0 },
      { "hour": "01:00", "excess_kwh": 0.0 },
      { "hour": "02:00", "excess_kwh": 0.0 },
      { "hour": "03:00", "excess_kwh": 0.0 },
      { "hour": "04:00", "excess_kwh": 0.0 },
      { "hour": "05:00", "excess_kwh": 0.0 },
      { "hour": "06:00", "excess_kwh": 0.0 },
      { "hour": "07:00", "excess_kwh": 0.0 },
      { "hour": "08:00", "excess_kwh": 5.0 },
      { "hour": "09:00", "excess_kwh": 9.02 },
      { "hour": "10:00", "excess_kwh": 16.36 },
      { "hour": "11:00", "excess_kwh": 16.41 },
      { "hour": "12:00", "excess_kwh": 19.26 },
      { "hour": "13:00", "excess_kwh": 11.32 },
      { "hour": "14:00", "excess_kwh": 18.03 },
      { "hour": "15:00", "excess_kwh": 13.31 },
      { "hour": "16:00", "excess_kwh": 5.0 },
      { "hour": "17:00", "excess_kwh": 0.0 },
      { "hour": "18:00", "excess_kwh": 0.0 },
      { "hour": "19:00", "excess_kwh": 0.0 },
      { "hour": "20:00", "excess_kwh": 0.0 },
      { "hour": "21:00", "excess_kwh": 0.0 },
      { "hour": "22:00", "excess_kwh": 0.0 },
      { "hour": "23:00", "excess_kwh": 0.0 }
    ]
  },
  {
    "date": "2026-02-07",
    "hourly": [
      { "hour": "00:00", "excess_kwh": 0.0 },
      { "hour": "01:00", "excess_kwh": 0.0 },
      { "hour": "02:00", "excess_kwh": 0.0 },
      { "hour": "03:00", "excess_kwh": 0.0 },
      { "hour": "04:00", "excess_kwh": 0.0 },
      { "hour": "05:00", "excess_kwh": 0.0 },
      { "hour": "06:00", "excess_kwh": 0.0 },
      { "hour": "07:00", "excess_kwh": 0.0 },
      { "hour": "08:00", "excess_kwh": 5.0 },
      { "hour": "09:00", "excess_kwh": 9.02 },
      { "hour": "10:00", "excess_kwh": 16.36 },
      { "hour": "11:00", "excess_kwh": 16.41 },
      { "hour": "12:00", "excess_kwh": 19.26 },
      { "hour": "13:00", "excess_kwh": 11.32 },
      { "hour": "14:00", "excess_kwh": 18.03 },
      { "hour": "15:00", "excess_kwh": 13.31 },
      { "hour": "16:00", "excess_kwh": 5.0 },
      { "hour": "17:00", "excess_kwh": 0.0 },
      { "hour": "18:00", "excess_kwh": 0.0 },
      { "hour": "19:00", "excess_kwh": 0.0 },
      { "hour": "20:00", "excess_kwh": 0.0 },
      { "hour": "21:00", "excess_kwh": 0.0 },
      { "hour": "22:00", "excess_kwh": 0.0 },
      { "hour": "23:00", "excess_kwh": 0.0 }
    ]
  },
  {
    "date": "2026-02-08",
    "hourly": [
      { "hour": "00:00", "excess_kwh": 0.0 },
      { "hour": "01:00", "excess_kwh": 0.0 },
      { "hour": "02:00", "excess_kwh": 0.0 },
      { "hour": "03:00", "excess_kwh": 0.0 },
      { "hour": "04:00", "excess_kwh": 0.0 },
      { "hour": "05:00", "excess_kwh": 0.0 },
      { "hour": "06:00", "excess_kwh": 0.45 },
      { "hour": "07:00", "excess_kwh": 1.0 },
      { "hour": "08:00", "excess_kwh": 4.5 },
      { "hour": "09:00", "excess_kwh": 8.19 },
      { "hour": "10:00", "excess_kwh": 16.69 },
      { "hour": "11:00", "excess_kwh": 14.07 },
      { "hour": "12:00", "excess_kwh": 16.41 },
      { "hour": "13:00", "excess_kwh": 12.7 },
      { "hour": "14:00", "excess_kwh": 13.45 },
      { "hour": "15:00", "excess_kwh": 4.88 },
      { "hour": "16:00", "excess_kwh": 3.44 },
      { "hour": "17:00", "excess_kwh": 0.0 },
      { "hour": "18:00", "excess_kwh": 0.0 },
      { "hour": "19:00", "excess_kwh": 0.0 },
      { "hour": "20:00", "excess_kwh": 0.0 },
      { "hour": "21:00", "excess_kwh": 0.0 },
      { "hour": "22:00", "excess_kwh": 0.0 },
      { "hour": "23:00", "excess_kwh": 0.0 }
    ]
  },
  {
    "date": "2026-02-09",
    "hourly": [
      { "hour": "00:00", "excess_kwh": 0.0 },
      { "hour": "01:00", "excess_kwh": 0.0 },
      { "hour": "02:00", "excess_kwh": 0.0 },
      { "hour": "03:00", "excess_kwh": 0.0 },
      { "hour": "04:00", "excess_kwh": 0.0 },
      { "hour": "05:00", "excess_kwh": 0.0 },
      { "hour": "06:00", "excess_kwh": 0.0 },
      { "hour": "07:00", "excess_kwh": 0.0 },
      { "hour": "08:00", "excess_kwh": 5.9 },
      { "hour": "09:00", "excess_kwh": 6.51 },
      { "hour": "10:00", "excess_kwh": 15.12 },
      { "hour": "11:00", "excess_kwh": 16.81 },
      { "hour": "12:00", "excess_kwh": 16.24 },
      { "hour": "13:00", "excess_kwh": 9.61 },
      { "hour": "14:00", "excess_kwh": 9.58 },
      { "hour": "15:00", "excess_kwh": 5.43 },
      { "hour": "16:00", "excess_kwh": 5.86 },
      { "hour": "17:00", "excess_kwh": 0.0 },
      { "hour": "18:00", "excess_kwh": 0.0 },
      { "hour": "19:00", "excess_kwh": 0.0 },
      { "hour": "20:00", "excess_kwh": 0.0 },
      { "hour": "21:00", "excess_kwh": 0.0 },
      { "hour": "22:00", "excess_kwh": 0.0 },
      { "hour": "23:00", "excess_kwh": 0.0 }
    ]
  },
  {
    "date": "2026-02-10",
    "hourly": [
      { "hour": "00:00", "excess_kwh": 0.0 },
      { "hour": "01:00", "excess_kwh": 0.0 },
      { "hour": "02:00", "excess_kwh": 0.0 },
      { "hour": "03:00", "excess_kwh": 0.0 },
      { "hour": "04:00", "excess_kwh": 0.0 },
      { "hour": "05:00", "excess_kwh": 0.0 },
      { "hour": "06:00", "excess_kwh": 0.0 },
      { "hour": "07:00", "excess_kwh": 0.51 },
      { "hour": "08:00", "excess_kwh": 5.09 },
      { "hour": "09:00", "excess_kwh": 6.66 },
      { "hour": "10:00", "excess_kwh": 15.59 },
      { "hour": "11:00", "excess_kwh": 16.23 },
      { "hour": "12:00", "excess_kwh": 17.8 },
      { "hour": "13:00", "excess_kwh": 13.32 },
      { "hour": "14:00", "excess_kwh": 11.47 },
      { "hour": "15:00", "excess_kwh": 6.33 },
      { "hour": "16:00", "excess_kwh": 3.83 },
      { "hour": "17:00", "excess_kwh": 0.0 },
      { "hour": "18:00", "excess_kwh": 0.73 },
      { "hour": "19:00", "excess_kwh": 0.0 },
      { "hour": "20:00", "excess_kwh": 0.0 },
      { "hour": "21:00", "excess_kwh": 0.0 },
      { "hour": "22:00", "excess_kwh": 0.0 },
      { "hour": "23:00", "excess_kwh": 0.0 }
    ]
  },
  {
    "date": "2026-02-11",
    "hourly": [
      { "hour": "00:00", "excess_kwh": 0.0 },
      { "hour": "01:00", "excess_kwh": 0.0 },
      { "hour": "02:00", "excess_kwh": 0.0 },
      { "hour": "03:00", "excess_kwh": 0.0 },
      { "hour": "04:00", "excess_kwh": 0.0 },
      { "hour": "05:00", "excess_kwh": 0.0 },
      { "hour": "06:00", "excess_kwh": 0.0 },
      { "hour": "07:00", "excess_kwh": 1.91 },
      { "hour": "08:00", "excess_kwh": 5.16 },
      { "hour": "09:00", "excess_kwh": 8.61 },
      { "hour": "10:00", "excess_kwh": 15.71 },
      { "hour": "11:00", "excess_kwh": 17.98 },
      { "hour": "12:00", "excess_kwh": 17.25 },
      { "hour": "13:00", "excess_kwh": 15.97 },
      { "hour": "14:00", "excess_kwh": 16.91 },
      { "hour": "15:00", "excess_kwh": 8.26 },
      { "hour": "16:00", "excess_kwh": 3.69 },
      { "hour": "17:00", "excess_kwh": 0.0 },
      { "hour": "18:00", "excess_kwh": 0.0 },
      { "hour": "19:00", "excess_kwh": 0.0 },
      { "hour": "20:00", "excess_kwh": 0.0 },
      { "hour": "21:00", "excess_kwh": 0.0 },
      { "hour": "22:00", "excess_kwh": 0.0 },
      { "hour": "23:00", "excess_kwh": 0.0 }
    ]
  },
  {
    "date": "2026-02-12",
    "hourly": [
      { "hour": "00:00", "excess_kwh": 0.0 },
      { "hour": "01:00", "excess_kwh": 0.0 },
      { "hour": "02:00", "excess_kwh": 0.0 },
      { "hour": "03:00", "excess_kwh": 0.0 },
      { "hour": "04:00", "excess_kwh": 0.0 },
      { "hour": "05:00", "excess_kwh": 0.0 },
      { "hour": "06:00", "excess_kwh": 0.0 },
      { "hour": "07:00", "excess_kwh": 1.0 },
      { "hour": "08:00", "excess_kwh": 4.31 },
      { "hour": "09:00", "excess_kwh": 6.29 },
      { "hour": "10:00", "excess_kwh": 14.03 },
      { "hour": "11:00", "excess_kwh": 13.72 },
      { "hour": "12:00", "excess_kwh": 15.25 },
      { "hour": "13:00", "excess_kwh": 14.6 },
      { "hour": "14:00", "excess_kwh": 7.66 },
      { "hour": "15:00", "excess_kwh": 12.29 },
      { "hour": "16:00", "excess_kwh": 2.26 },
      { "hour": "17:00", "excess_kwh": 2.01 },
      { "hour": "18:00", "excess_kwh": 0.0 },
      { "hour": "19:00", "excess_kwh": 0.0 },
      { "hour": "20:00", "excess_kwh": 0.0 },
      { "hour": "21:00", "excess_kwh": 0.0 },
      { "hour": "22:00", "excess_kwh": 0.0 },
      { "hour": "23:00", "excess_kwh": 0.0 }
    ]
  },
  {
    "date": "2026-02-13",
    "hourly": [
      { "hour": "00:00", "excess_kwh": 0.0 },
      { "hour": "01:00", "excess_kwh": 0.0 },
      { "hour": "02:00", "excess_kwh": 0.0 },
      { "hour": "03:00", "excess_kwh": 0.0 },
      { "hour": "04:00", "excess_kwh": 0.0 },
      { "hour": "05:00", "excess_kwh": 0.0 },
      { "hour": "06:00", "excess_kwh": 0.40 },
      { "hour": "07:00", "excess_kwh": 0.53 },
      { "hour": "08:00", "excess_kwh": 4.44 },
      { "hour": "09:00", "excess_kwh": 6.92 },
      { "hour": "10:00", "excess_kwh": 11.41 },
      { "hour": "11:00", "excess_kwh": 12.19 },
      { "hour": "12:00", "excess_kwh": 14.59 },
      { "hour": "13:00", "excess_kwh": 15.97 },
      { "hour": "14:00", "excess_kwh": 13.56 },
      { "hour": "15:00", "excess_kwh": 7.05 },
      { "hour": "16:00", "excess_kwh": 5.47 },
      { "hour": "17:00", "excess_kwh": 0.0 },
      { "hour": "18:00", "excess_kwh": 0.0 },
      { "hour": "19:00", "excess_kwh": 0.0 },
      { "hour": "20:00", "excess_kwh": 0.0 },
      { "hour": "21:00", "excess_kwh": 0.0 },
      { "hour": "22:00", "excess_kwh": 0.0 },
      { "hour": "23:00", "excess_kwh": 0.0 }
    ]
  },
  {
    "date": "2026-02-14",
    "hourly": [
      { "hour": "00:00", "excess_kwh": 0.0 },
      { "hour": "01:00", "excess_kwh": 0.0 },
      { "hour": "02:00", "excess_kwh": 0.0 },
      { "hour": "03:00", "excess_kwh": 0.0 },
      { "hour": "04:00", "excess_kwh": 0.0 },
      { "hour": "05:00", "excess_kwh": 0.0 },
      { "hour": "06:00", "excess_kwh": 0.0 },
      { "hour": "07:00", "excess_kwh": 0.0 },
      { "hour": "08:00", "excess_kwh": 4.83 },
      { "hour": "09:00", "excess_kwh": 8.2 },
      { "hour": "10:00", "excess_kwh": 14.34 },
      { "hour": "11:00", "excess_kwh": 15.43 },
      { "hour": "12:00", "excess_kwh": 16.61 },
      { "hour": "13:00", "excess_kwh": 13.84 },
      { "hour": "14:00", "excess_kwh": 7.67 },
      { "hour": "15:00", "excess_kwh": 4.78 },
      { "hour": "16:00", "excess_kwh": 4.34 },
      { "hour": "17:00", "excess_kwh": 1.08 },
      { "hour": "18:00", "excess_kwh": 0.0 },
      { "hour": "19:00", "excess_kwh": 0.0 },
      { "hour": "20:00", "excess_kwh": 0.0 },
      { "hour": "21:00", "excess_kwh": 0.0 },
      { "hour": "22:00", "excess_kwh": 0.0 },
      { "hour": "23:00", "excess_kwh": 0.0 }
    ]
  },
  {
    "date": "2026-02-15",
    "hourly": [
      { "hour": "00:00", "excess_kwh": 0.0 },
      { "hour": "01:00", "excess_kwh": 0.0 },
      { "hour": "02:00", "excess_kwh": 0.0 },
      { "hour": "03:00", "excess_kwh": 0.0 },
      { "hour": "04:00", "excess_kwh": 0.0 },
      { "hour": "05:00", "excess_kwh": 0.0 },
      { "hour": "06:00", "excess_kwh": 0.0 },
      { "hour": "07:00", "excess_kwh": 2.36 },
      { "hour": "08:00", "excess_kwh": 4.28 },
      { "hour": "09:00", "excess_kwh": 10.2 },
      { "hour": "10:00", "excess_kwh": 15.59 },
      { "hour": "11:00", "excess_kwh": 18.83 },
      { "hour": "12:00", "excess_kwh": 19.99 },
      { "hour": "13:00", "excess_kwh": 11.75 },
      { "hour": "14:00", "excess_kwh": 13.98 },
      { "hour": "15:00", "excess_kwh": 6.33 },
      { "hour": "16:00", "excess_kwh": 5.34 },
      { "hour": "17:00", "excess_kwh": 2.53 },
      { "hour": "18:00", "excess_kwh": 0.0 },
      { "hour": "19:00", "excess_kwh": 0.0 },
      { "hour": "20:00", "excess_kwh": 0.0 },
      { "hour": "21:00", "excess_kwh": 0.0 },
      { "hour": "22:00", "excess_kwh": 0.0 },
      { "hour": "23:00", "excess_kwh": 0.0 }
    ]
  },
  {
    "date": "2026-02-16",
    "hourly": [
      { "hour": "00:00", "excess_kwh": 0.0 },
      { "hour": "01:00", "excess_kwh": 0.0 },
      { "hour": "02:00", "excess_kwh": 0.0 },
      { "hour": "03:00", "excess_kwh": 0.0 },
      { "hour": "04:00", "excess_kwh": 0.0 },
      { "hour": "05:00", "excess_kwh": 0.0 },
      { "hour": "06:00", "excess_kwh": 0.0 },
      { "hour": "07:00", "excess_kwh": 0.0 },
      { "hour": "08:00", "excess_kwh": 3.6 },
      { "hour": "09:00", "excess_kwh": 5.5 },
      { "hour": "10:00", "excess_kwh": 15.31 },
      { "hour": "11:00", "excess_kwh": 13.37 },
      { "hour": "12:00", "excess_kwh": 17.02 },
      { "hour": "13:00", "excess_kwh": 12.02 },
      { "hour": "14:00", "excess_kwh": 9.28 },
      { "hour": "15:00", "excess_kwh": 9.27 },
      { "hour": "16:00", "excess_kwh": 2.36 },
      { "hour": "17:00", "excess_kwh": 0.7 },
      { "hour": "18:00", "excess_kwh": 0.0 },
      { "hour": "19:00", "excess_kwh": 0.0 },
      { "hour": "20:00", "excess_kwh": 0.0 },
      { "hour": "21:00", "excess_kwh": 0.0 },
      { "hour": "22:00", "excess_kwh": 0.0 },
      { "hour": "23:00", "excess_kwh": 0.0 }
    ]
  },
  {
    "date": "2026-02-17",
    "hourly": [
      { "hour": "00:00", "excess_kwh": 0.0 },
      { "hour": "01:00", "excess_kwh": 0.0 },
      { "hour": "02:00", "excess_kwh": 0.0 },
      { "hour": "03:00", "excess_kwh": 0.0 },
      { "hour": "04:00", "excess_kwh": 0.0 },
      { "hour": "05:00", "excess_kwh": 0.0 },
      { "hour": "06:00", "excess_kwh": 0.35 },
      { "hour": "07:00", "excess_kwh": 2.39 },
      { "hour": "08:00", "excess_kwh": 3.16 },
      { "hour": "09:00", "excess_kwh": 5.93 },
      { "hour": "10:00", "excess_kwh": 13.96 },
      { "hour": "11:00", "excess_kwh": 14.13 },
      { "hour": "12:00", "excess_kwh": 15.82 },
      { "hour": "13:00", "excess_kwh": 13.7 },
      { "hour": "14:00", "excess_kwh": 15.11 },
      { "hour": "15:00", "excess_kwh": 8.36 },
      { "hour": "16:00", "excess_kwh": 5.09 },
      { "hour": "17:00", "excess_kwh": 1.6 },
      { "hour": "18:00", "excess_kwh": 0.0 },
      { "hour": "19:00", "excess_kwh": 0.0 },
      { "hour": "20:00", "excess_kwh": 0.0 },
      { "hour": "21:00", "excess_kwh": 0.0 },
      { "hour": "22:00", "excess_kwh": 0.0 },
      { "hour": "23:00", "excess_kwh": 0.0 }
    ]
  },
  {
    "date": "2026-02-18",
    "hourly": [
      { "hour": "00:00", "excess_kwh": 0.0 },
      { "hour": "01:00", "excess_kwh": 0.0 },
      { "hour": "02:00", "excess_kwh": 0.0 },
      { "hour": "03:00", "excess_kwh": 0.0 },
      { "hour": "04:00", "excess_kwh": 0.0 },
      { "hour": "05:00", "excess_kwh": 0.0 },
      { "hour": "06:00", "excess_kwh": 0.27 },
      { "hour": "07:00", "excess_kwh": 0.0 },
      { "hour": "08:00", "excess_kwh": 4.12 },
      { "hour": "09:00", "excess_kwh": 5.82 },
      { "hour": "10:00", "excess_kwh": 14.1 },
      { "hour": "11:00", "excess_kwh": 15.08 },
      { "hour": "12:00", "excess_kwh": 19.94 },
      { "hour": "13:00", "excess_kwh": 12.51 },
      { "hour": "14:00", "excess_kwh": 17.95 },
      { "hour": "15:00", "excess_kwh": 13.97 },
      { "hour": "16:00", "excess_kwh": 6.5 },
      { "hour": "17:00", "excess_kwh": 1.69 },
      { "hour": "18:00", "excess_kwh": 0.0 },
      { "hour": "19:00", "excess_kwh": 0.0 },
      { "hour": "20:00", "excess_kwh": 0.0 },
      { "hour": "21:00", "excess_kwh": 0.0 },
      { "hour": "22:00", "excess_kwh": 0.0 },
      { "hour": "23:00", "excess_kwh": 0.0 }
    ]
  },
  {
    "date": "2026-02-19",
    "hourly": [
      { "hour": "00:00", "excess_kwh": 0.0 },
      { "hour": "01:00", "excess_kwh": 0.0 },
      { "hour": "02:00", "excess_kwh": 0.0 },
      { "hour": "03:00", "excess_kwh": 0.0 },
      { "hour": "04:00", "excess_kwh": 0.0 },
      { "hour": "05:00", "excess_kwh": 0.0 },
      { "hour": "06:00", "excess_kwh": 0.38 },
      { "hour": "07:00", "excess_kwh": 0.96 },
      { "hour": "08:00", "excess_kwh": 3.09 },
      { "hour": "09:00", "excess_kwh": 5.79 },
      { "hour": "10:00", "excess_kwh": 12.31 },
      { "hour": "11:00", "excess_kwh": 13.33 },
      { "hour": "12:00", "excess_kwh": 16.46 },
      { "hour": "13:00", "excess_kwh": 13.73 },
      { "hour": "14:00", "excess_kwh": 14.75 },
      { "hour": "15:00", "excess_kwh": 6.66 },
      { "hour": "16:00", "excess_kwh": 5.36 },
      { "hour": "17:00", "excess_kwh": 0.0 },
      { "hour": "18:00", "excess_kwh": 0.0 },
      { "hour": "19:00", "excess_kwh": 0.0 },
      { "hour": "20:00", "excess_kwh": 0.0 },
      { "hour": "21:00", "excess_kwh": 0.0 },
      { "hour": "22:00", "excess_kwh": 0.0 },
      { "hour": "23:00", "excess_kwh": 0.0 }
    ]
  },
  {
    "date": "2026-02-20",
    "hourly": [
      { "hour": "00:00", "excess_kwh": 0.0 },
      { "hour": "01:00", "excess_kwh": 0.0 },
      { "hour": "02:00", "excess_kwh": 0.0 },
      { "hour": "03:00", "excess_kwh": 0.0 },
      { "hour": "04:00", "excess_kwh": 0.0 },
      { "hour": "05:00", "excess_kwh": 0.0 },
      { "hour": "06:00", "excess_kwh": 0.0 },
      { "hour": "07:00", "excess_kwh": 1.03 },
      { "hour": "08:00", "excess_kwh": 3.77 },
      { "hour": "09:00", "excess_kwh": 9.95 },
      { "hour": "10:00", "excess_kwh": 14.83 },
      { "hour": "11:00", "excess_kwh": 18.72 },
      { "hour": "12:00", "excess_kwh": 18.31 },
      { "hour": "13:00", "excess_kwh": 12.61 },
      { "hour": "14:00", "excess_kwh": 18.82 },
      { "hour": "15:00", "excess_kwh": 6.41 },
      { "hour": "16:00", "excess_kwh": 4.45 },
      { "hour": "17:00", "excess_kwh": 1.52 },
      { "hour": "18:00", "excess_kwh": 0.0 },
      { "hour": "19:00", "excess_kwh": 0.0 },
      { "hour": "20:00", "excess_kwh": 0.0 },
      { "hour": "21:00", "excess_kwh": 0.0 },
      { "hour": "22:00", "excess_kwh": 0.0 },
      { "hour": "23:00", "excess_kwh": 0.0 }
    ]
  },
  {
    "date": "2026-02-21",
    "hourly": [
      { "hour": "00:00", "excess_kwh": 0.0 },
      { "hour": "01:00", "excess_kwh": 0.0 },
      { "hour": "02:00", "excess_kwh": 0.0 },
      { "hour": "03:00", "excess_kwh": 0.0 },
      { "hour": "04:00", "excess_kwh": 0.0 },
      { "hour": "05:00", "excess_kwh": 0.0 },
      { "hour": "06:00", "excess_kwh": 0.16 },
      { "hour": "07:00", "excess_kwh": 2.06 },
      { "hour": "08:00", "excess_kwh": 5.92 },
      { "hour": "09:00", "excess_kwh": 6.67 },
      { "hour": "10:00", "excess_kwh": 18.78 },
      { "hour": "11:00", "excess_kwh": 16.89 },
      { "hour": "12:00", "excess_kwh": 18.76 },
      { "hour": "13:00", "excess_kwh": 10.42 },
      { "hour": "14:00", "excess_kwh": 14.31 },
      { "hour": "15:00", "excess_kwh": 14.55 },
      { "hour": "16:00", "excess_kwh": 4.12 },
      { "hour": "17:00", "excess_kwh": 0.0 },
      { "hour": "18:00", "excess_kwh": 0.0 },
      { "hour": "19:00", "excess_kwh": 0.0 },
      { "hour": "20:00", "excess_kwh": 0.0 },
      { "hour": "21:00", "excess_kwh": 0.0 },
      { "hour": "22:00", "excess_kwh": 0.0 },
      { "hour": "23:00", "excess_kwh": 0.0 }
    ]
  },
  {
    "date": "2026-02-22",
    "hourly": [
      { "hour": "00:00", "excess_kwh": 0.0 },
      { "hour": "01:00", "excess_kwh": 0.0 },
      { "hour": "02:00", "excess_kwh": 0.0 },
      { "hour": "03:00", "excess_kwh": 0.0 },
      { "hour": "04:00", "excess_kwh": 0.0 },
      { "hour": "05:00", "excess_kwh": 0.0 },
      { "hour": "06:00", "excess_kwh": 0.0 },
      { "hour": "07:00", "excess_kwh": 2.43 },
      { "hour": "08:00", "excess_kwh": 5.28 },
      { "hour": "09:00", "excess_kwh": 6.58 },
      { "hour": "10:00", "excess_kwh": 15.5 },
      { "hour": "11:00", "excess_kwh": 14.89 },
      { "hour": "12:00", "excess_kwh": 16.78 },
      { "hour": "13:00", "excess_kwh": 11.16 },
      { "hour": "14:00", "excess_kwh": 12.68 },
      { "hour": "15:00", "excess_kwh": 5.42 },
      { "hour": "16:00", "excess_kwh": 2.47 },
      { "hour": "17:00", "excess_kwh": 2.37 },
      { "hour": "18:00", "excess_kwh": 0.0 },
      { "hour": "19:00", "excess_kwh": 0.0 },
      { "hour": "20:00", "excess_kwh": 0.0 },
      { "hour": "21:00", "excess_kwh": 0.0 },
      { "hour": "22:00", "excess_kwh": 0.0 },
      { "hour": "23:00", "excess_kwh": 0.0 }
    ]
  },
  {
    "date": "2026-02-23",
    "hourly": [
      { "hour": "00:00", "excess_kwh": 0.0 },
      { "hour": "01:00", "excess_kwh": 0.0 },
      { "hour": "02:00", "excess_kwh": 0.0 },
      { "hour": "03:00", "excess_kwh": 0.0 },
      { "hour": "04:00", "excess_kwh": 0.0 },
      { "hour": "05:00", "excess_kwh": 0.0 },
      { "hour": "06:00", "excess_kwh": 0.16 },
      { "hour": "07:00", "excess_kwh": 1.0 },
      { "hour": "08:00", "excess_kwh": 4.28 },
      { "hour": "09:00", "excess_kwh": 6.64 },
      { "hour": "10:00", "excess_kwh": 14.96 },
      { "hour": "11:00", "excess_kwh": 16.49 },
      { "hour": "12:00", "excess_kwh": 18.11 },
      { "hour": "13:00", "excess_kwh": 16.38 },
      { "hour": "14:00", "excess_kwh": 8.72 },
      { "hour": "15:00", "excess_kwh": 8.36 },
      { "hour": "16:00", "excess_kwh": 5.93 },
      { "hour": "17:00", "excess_kwh": 1.07 },
      { "hour": "18:00", "excess_kwh": 0.35 },
      { "hour": "19:00", "excess_kwh": 0.0 },
      { "hour": "20:00", "excess_kwh": 0.0 },
      { "hour": "21:00", "excess_kwh": 0.0 },
      { "hour": "22:00", "excess_kwh": 0.0 },
      { "hour": "23:00", "excess_kwh": 0.0 }
    ]
  },
  {
    "date": "2026-02-24",
    "hourly": [
      { "hour": "00:00", "excess_kwh": 0.0 },
      { "hour": "01:00", "excess_kwh": 0.0 },
      { "hour": "02:00", "excess_kwh": 0.0 },
      { "hour": "03:00", "excess_kwh": 0.0 },
      { "hour": "04:00", "excess_kwh": 0.0 },
      { "hour": "05:00", "excess_kwh": 0.0 },
      { "hour": "06:00", "excess_kwh": 0.0 },
      { "hour": "07:00", "excess_kwh": 1.38 },
      { "hour": "08:00", "excess_kwh": 4.92 },
      { "hour": "09:00", "excess_kwh": 6.42 },
      { "hour": "10:00", "excess_kwh": 15.68 },
      { "hour": "11:00", "excess_kwh": 19.28 },
      { "hour": "12:00", "excess_kwh": 18.89 },
      { "hour": "13:00", "excess_kwh": 13.15 },
      { "hour": "14:00", "excess_kwh": 16.62 },
      { "hour": "15:00", "excess_kwh": 11.26 },
      { "hour": "16:00", "excess_kwh": 5.41 },
      { "hour": "17:00", "excess_kwh": 0.0 },
      { "hour": "18:00", "excess_kwh": 0.0 },
      { "hour": "19:00", "excess_kwh": 0.0 },
      { "hour": "20:00", "excess_kwh": 0.0 },
      { "hour": "21:00", "excess_kwh": 0.0 },
      { "hour": "22:00", "excess_kwh": 0.0 },
      { "hour": "23:00", "excess_kwh": 0.0 }
    ]
  },
  {
    "date": "2026-02-25",
    "hourly": [
      { "hour": "00:00", "excess_kwh": 0.0 },
      { "hour": "01:00", "excess_kwh": 0.0 },
      { "hour": "02:00", "excess_kwh": 0.0 },
      { "hour": "03:00", "excess_kwh": 0.0 },
      { "hour": "04:00", "excess_kwh": 0.0 },
      { "hour": "05:00", "excess_kwh": 0.0 },
      { "hour": "06:00", "excess_kwh": 0.0 },
      { "hour": "07:00", "excess_kwh": 0.84 },
      { "hour": "08:00", "excess_kwh": 4.34 },
      { "hour": "09:00", "excess_kwh": 7.21 },
      { "hour": "10:00", "excess_kwh": 17.26 },
      { "hour": "11:00", "excess_kwh": 18.4 },
      { "hour": "12:00", "excess_kwh": 21.76 },
      { "hour": "13:00", "excess_kwh": 12.42 },
      { "hour": "14:00", "excess_kwh": 9.82 },
      { "hour": "15:00", "excess_kwh": 13.54 },
      { "hour": "16:00", "excess_kwh": 6.02 },
      { "hour": "17:00", "excess_kwh": 0.0 },
      { "hour": "18:00", "excess_kwh": 0.63 },
      { "hour": "19:00", "excess_kwh": 0.0 },
      { "hour": "20:00", "excess_kwh": 0.0 },
      { "hour": "21:00", "excess_kwh": 0.0 },
      { "hour": "22:00", "excess_kwh": 0.0 },
      { "hour": "23:00", "excess_kwh": 0.0 }
    ]
  },
  {
    "date": "2026-02-26",
    "hourly": [
      { "hour": "00:00", "excess_kwh": 0.0 },
      { "hour": "01:00", "excess_kwh": 0.0 },
      { "hour": "02:00", "excess_kwh": 0.0 },
      { "hour": "03:00", "excess_kwh": 0.0 },
      { "hour": "04:00", "excess_kwh": 0.0 },
      { "hour": "05:00", "excess_kwh": 0.0 },
      { "hour": "06:00", "excess_kwh": 0.0 },
      { "hour": "07:00", "excess_kwh": 1.33 },
      { "hour": "08:00", "excess_kwh": 5.03 },
      { "hour": "09:00", "excess_kwh": 7.49 },
      { "hour": "10:00", "excess_kwh": 14.48 },
      { "hour": "11:00", "excess_kwh": 17.52 },
      { "hour": "12:00", "excess_kwh": 18.87 },
      { "hour": "13:00", "excess_kwh": 19.74 },
      { "hour": "14:00", "excess_kwh": 13.48 },
      { "hour": "15:00", "excess_kwh": 7.18 },
      { "hour": "16:00", "excess_kwh": 6.63 },
      { "hour": "17:00", "excess_kwh": 0.99 },
      { "hour": "18:00", "excess_kwh": 0.68 },
      { "hour": "19:00", "excess_kwh": 0.0 },
      { "hour": "20:00", "excess_kwh": 0.0 },
      { "hour": "21:00", "excess_kwh": 0.0 },
      { "hour": "22:00", "excess_kwh": 0.0 },
      { "hour": "23:00", "excess_kwh": 0.0 }
    ]
  },
  {
    "date": "2026-02-27",
    "hourly": [
      { "hour": "00:00", "excess_kwh": 0.0 },
      { "hour": "01:00", "excess_kwh": 0.0 },
      { "hour": "02:00", "excess_kwh": 0.0 },
      { "hour": "03:00", "excess_kwh": 0.0 },
      { "hour": "04:00", "excess_kwh": 0.0 },
      { "hour": "05:00", "excess_kwh": 0.0 },
      { "hour": "06:00", "excess_kwh": 0.0 },
      { "hour": "07:00", "excess_kwh": 0.0 },
      { "hour": "08:00", "excess_kwh": 3.18 },
      { "hour": "09:00", "excess_kwh": 7.03 },
      { "hour": "10:00", "excess_kwh": 13.77 },
      { "hour": "11:00", "excess_kwh": 13.2 },
      { "hour": "12:00", "excess_kwh": 15.74 },
      { "hour": "13:00", "excess_kwh": 11.5 },
      { "hour": "14:00", "excess_kwh": 12.02 },
      { "hour": "15:00", "excess_kwh": 4.94 },
      { "hour": "16:00", "excess_kwh": 2.93 },
      { "hour": "17:00", "excess_kwh": 0.8 },
      { "hour": "18:00", "excess_kwh": 0.0 },
      { "hour": "19:00", "excess_kwh": 0.0 },
      { "hour": "20:00", "excess_kwh": 0.0 },
      { "hour": "21:00", "excess_kwh": 0.0 },
      { "hour": "22:00", "excess_kwh": 0.0 },
      { "hour": "23:00", "excess_kwh": 0.0 }
    ]
  },
  {
    "date": "2026-02-28",
    "hourly": [
      { "hour": "00:00", "excess_kwh": 0.0 },
      { "hour": "01:00", "excess_kwh": 0.0 },
      { "hour": "02:00", "excess_kwh": 0.0 },
      { "hour": "03:00", "excess_kwh": 0.0 },
      { "hour": "04:00", "excess_kwh": 0.0 },
      { "hour": "05:00", "excess_kwh": 0.0 },
      { "hour": "06:00", "excess_kwh": 0.0 },
      { "hour": "07:00", "excess_kwh": 0.53 },
      { "hour": "08:00", "excess_kwh": 4.63 },
      { "hour": "09:00", "excess_kwh": 6.25 },
      { "hour": "10:00", "excess_kwh": 10.73 },
      { "hour": "11:00", "excess_kwh": 13.14 },
      { "hour": "12:00", "excess_kwh": 14.03 },
      { "hour": "13:00", "excess_kwh": 13.77 },
      { "hour": "14:00", "excess_kwh": 7.53 },
      { "hour": "15:00", "excess_kwh": 10.04 },
      { "hour": "16:00", "excess_kwh": 2.13 },
      { "hour": "17:00", "excess_kwh": 2.09 },
      { "hour": "18:00", "excess_kwh": 0.66 },
      { "hour": "19:00", "excess_kwh": 0.0 },
      { "hour": "20:00", "excess_kwh": 0.0 },
      { "hour": "21:00", "excess_kwh": 0.0 },
      { "hour": "22:00", "excess_kwh": 0.0 },
      { "hour": "23:00", "excess_kwh": 0.0 }
    ]
  },
  {
    "date": "2026-03-01",
    "hourly": [
      { "hour": "00:00", "excess_kwh": 0.0 },
      { "hour": "01:00", "excess_kwh": 0.0 },
      { "hour": "02:00", "excess_kwh": 0.0 },
      { "hour": "03:00", "excess_kwh": 0.0 },
      { "hour": "04:00", "excess_kwh": 0.0 },
      { "hour": "05:00", "excess_kwh": 0.0 },
      { "hour": "06:00", "excess_kwh": 0.43 },
      { "hour": "07:00", "excess_kwh": 2.0 },
      { "hour": "08:00", "excess_kwh": 3.47 },
      { "hour": "09:00", "excess_kwh": 6.34 },
      { "hour": "10:00", "excess_kwh": 12.89 },
      { "hour": "11:00", "excess_kwh": 15.95 },
      { "hour": "12:00", "excess_kwh": 17.35 },
      { "hour": "13:00", "excess_kwh": 10.29 },
      { "hour": "14:00", "excess_kwh": 11.52 },
      { "hour": "15:00", "excess_kwh": 7.38 },
      { "hour": "16:00", "excess_kwh": 4.99 },
      { "hour": "17:00", "excess_kwh": 0.0 },
      { "hour": "18:00", "excess_kwh": 0.0 },
      { "hour": "19:00", "excess_kwh": 0.0 },
      { "hour": "20:00", "excess_kwh": 0.0 },
      { "hour": "21:00", "excess_kwh": 0.0 },
      { "hour": "22:00", "excess_kwh": 0.0 },
      { "hour": "23:00", "excess_kwh": 0.0 }
    ]
  }
]
